wexample_filestate_dev-0.0.51.dist-info/METADATA
wexample_filestate_dev-0.0.51.dist-info/WHEEL
wexample_filestate_dev-0.0.51.dist-info/entry_points.txt
wexample_filestate_dev/__init__.py
wexample_filestate_dev/exception/__init__.py
wexample_filestate_dev/helpers/__init__.py
wexample_filestate_dev/py.typed
wexample_filestate_dev/workdir/__init__.py
wexample_filestate_dev-0.0.51.dist-info/RECORD
