Metadata-Version: 2.1
Name: wexample-filestate-dev
Version: 0.0.51
Summary: Some python basic helpers.
Author-Email: weeger <contact@wexample.com>
License: MIT
Classifier: Programming Language :: Python :: 3
Classifier: License :: OSI Approved :: MIT License
Classifier: Operating System :: OS Independent
Project-URL: homepage, https://github.com/wexample/python-filestate-dev
Requires-Python: >=3.10
Requires-Dist: attrs>=23.1.0
Requires-Dist: cattrs>=23.1.0
Requires-Dist: wexample-filestate==0.0.74
Provides-Extra: dev
Requires-Dist: pytest; extra == "dev"
Requires-Dist: pytest-cov; extra == "dev"
